MANIFEST.in
requirements.txt
setup.py
fastFET/FET.py
fastFET/MultiProcess.py
fastFET/README.md
fastFET/RIPEStatAPI.py
fastFET/__init__.py
fastFET/bgpToolKit.py
fastFET/collectData.py
fastFET/drawing.py
fastFET/event_list.csv
fastFET/featGraph.py
fastFET/featTradition.py
fastFET/featTree.py
fastFET/logConfig.json
fastFET/utils.py
fastFET.egg-info/PKG-INFO
fastFET.egg-info/SOURCES.txt
fastFET.egg-info/dependency_links.txt
fastFET.egg-info/requires.txt
fastFET.egg-info/top_level.txt
fastFET/BGPMAGNET/ProcessHandler.py
fastFET/BGPMAGNET/README.md
fastFET/BGPMAGNET/__init__.py
fastFET/BGPMAGNET/base.py
fastFET/BGPMAGNET/dataGetter.py
fastFET/BGPMAGNET/download.py
fastFET/BGPMAGNET/params.py
fastFET/BGPMAGNET/parse.py
fastFET/BGPMAGNET/tools.py
fastFET/BGPMAGNET/bgpparser/__init__.py
fastFET/BGPMAGNET/bgpparser/base.py
fastFET/BGPMAGNET/bgpparser/dump_form.py
fastFET/BGPMAGNET/bgpparser/init.py
fastFET/BGPMAGNET/bgpparser/params.py
fastFET/BGPMAGNET/bgpparser/parse.py
fastFET/BGPMAGNET/bgpparser/parse_Process.py
fastFET/BGPMAGNET/bgpparser/read_Process.py
fastFET/BGPMAGNET/config/collector_list.ini
fastFET/BGPMAGNET/config/parseMRT.ini