Metadata-Version: 2.1
Name: fastFET
Version: 0.0.7
Summary: A fast feature extrating tool for BGP Dataset Collection.
Home-page: https://github.com/JamesRay0713/fastFET
Author: James Ray
Author-email: hl1670704310@icloud.com
License: MIT
Classifier: Programming Language :: Python :: 3
Classifier: License :: OSI Approved :: MIT License
Classifier: Operating System :: OS Independent
Requires-Python: >=3.8.0
